Metadata-Version: 2.1
Name: MongodbDatabaseEngine
Version: 0.0.9
Summary: This python package is to create mongodb database, collections automatically using json file and can be integrated with API
Home-page: https://github.com/ashishcssom/MongodbDatabaseEngine
Author: Ashish Kumar
Author-email: ashish.krb7@gmail.com
License: MIT
Download-URL: https://github.com/ashishcssom/MongodbDatabaseEngine/archive/v_009.tar.gz
Keywords: MongoDb,API,Database,python,creater
Platform: UNKNOWN
Classifier: Development Status :: 5 - Production/Stable
Classifier: Intended Audience :: Developers
Classifier: Topic :: Software Development :: Build Tools
Classifier: License :: OSI Approved :: MIT License
Classifier: Programming Language :: Python :: 3
Classifier: Programming Language :: Python :: 3.4
Classifier: Programming Language :: Python :: 3.5
Classifier: Programming Language :: Python :: 3.6
Classifier: Programming Language :: Python :: 3.7
Classifier: Programming Language :: Python :: 3.8
Classifier: Programming Language :: Python :: 3.9
